{
"type": "FeatureCollection",
"name": "15",
"crs": { "type": "name", "properties": { "name": "urn:ogc:def:crs:OGC:1.3:CRS84" } },
"features": [
{ "type": "Feature", "properties": { "y": 51.460619, "x": -0.964706, "date": 15 }, "geometry": { "type": "Point", "coordinates": [ -0.964706, 51.460619 ] } }
]
}
